examples/__init__.py
examples/biology_solutions.py
tests/__init__.py
tests/test_base_arithmetic.py
tests/test_derived_units_arithmetic.py
tests/test_parsing.py
tests/test_sanity.py
units_calculator/__init__.py
units_calculator/all.py
units_calculator/py.typed
units_calculator/derived_units/__init__.py
units_calculator/derived_units/area_units.py
units_calculator/derived_units/chemistry_units.py
units_calculator/derived_units/length_units.py
units_calculator/derived_units/mass_units.py
units_calculator/derived_units/py.typed
units_calculator/derived_units/time_units.py
units_calculator/derived_units/volume_units.py
units_calculator/engine/__init__.py
units_calculator/engine/engine.py
units_calculator/engine/py.typed
units_calculator/si_units/__init__.py
units_calculator/si_units/py.typed
units_calculator/si_units/si_units.py
units_calculator-1.0.4.dist-info/LICENSE
units_calculator-1.0.4.dist-info/METADATA
units_calculator-1.0.4.dist-info/WHEEL
units_calculator-1.0.4.dist-info/top_level.txt
units_calculator-1.0.4.dist-info/RECORD
